viewUtilsOdoo/utils.py
viewutilsodoo-0.0.1.dist-info/METADATA
viewutilsodoo-0.0.1.dist-info/WHEEL
viewutilsodoo-0.0.1.dist-info/entry_points.txt
viewutilsodoo-0.0.1.dist-info/license_files/LICENSE
viewutilsodoo-0.0.1.dist-info/RECORD
