Metadata-Version: 2.1
Name: viewutilsodoo
Version: 0.0.1
Summary: Functions that allow to see and compare the information.
Project-URL: Bug Tracker, https://github.com/Caribbean-Digital-Group/viewUtilsOdoo/issues
Project-URL: Homepage, https://github.com/Caribbean-Digital-Group/viewUtilsOdoo
Author-email: JesusAlayonD <jesusalayond@gmail.com>
License: MIT License
Classifier: License :: OSI Approved :: MIT License
Classifier: Operating System :: OS Independent
Classifier: Programming Language :: Python :: 3
Requires-Python: >=3.6.9
